Metadata-Version: 2.1
Name: sohuprompt
Version: 1.0.7
Summary: A python lib for sohuprompt
Home-page: UNKNOWN
Author: senhaowang,chencheng
Author-email: senhaowang@sohu-inc.com
License: MIT
Platform: UNKNOWN
Requires-Dist: transformers
Requires-Dist: torch
Requires-Dist: numpy
Requires-Dist: pandas
Requires-Dist: tqdm
Requires-Dist: scikit-learn
Requires-Dist: jieba
Requires-Dist: tensorboard (==2.9.0)
Requires-Dist: icetk
Requires-Dist: yacs
Requires-Dist: rouge
Requires-Dist: openpyxl
Requires-Dist: tensorboardX
Requires-Dist: nltk
